cellmech/__init__.py
cellmech/bead_detection.py
cellmech/beads_generator.py
cellmech/fttc.py
cellmech/image_filter.py
cellmech/tensorop.py
cellmech/utils.py
cellmech-1.1.3.dist-info/METADATA
cellmech-1.1.3.dist-info/WHEEL
cellmech-1.1.3.dist-info/licenses/LICENSE
cellmech-1.1.3.dist-info/RECORD
