Metadata-Version: 2.4
Name: cellmech
Version: 1.1.3
Summary: 
License: MIT
License-File: LICENSE
Author: Utkarsh
Requires-Python: >=3.12
Classifier: License :: OSI Approved :: MIT License
Classifier: Programming Language :: Python :: 3
Classifier: Programming Language :: Python :: 3.12
Classifier: Programming Language :: Python :: 3.13
Classifier: Programming Language :: Python :: 3.14
Requires-Dist: ipykernel (>=7.1.0,<8.0.0)
Requires-Dist: numpy (>=2.3.4,<3.0.0)
Requires-Dist: pillow (>=12.0.0,<13.0.0)
Requires-Dist: pyqt6 (>=6.10.0,<7.0.0)
Requires-Dist: scipy (>=1.16.3,<2.0.0)
Requires-Dist: seaborn (>=0.13.2,<0.14.0)
